connectmon/__init__.py
connectmon/__main__.py
connectmon/api.py
connectmon/env.py
connectmon/logger.py
connectmon/messaging.py
connectmon/models.py
connectmon/utils.py
connectmon-0.2.7.dist-info/WHEEL
connectmon-0.2.7.dist-info/METADATA
connectmon-0.2.7.dist-info/RECORD
