Metadata-Version: 2.1
Name: connectmon
Version: 0.2.7
Summary: A tool for monitoring tasks and connectors in Kafka Connect.
Home-page: https://github.com/JenspederM/ConnectMon
Keywords: kafka,kafka connect,monitoring,connectmon
Author: Jens Peder Meldgaard
Author-email: jenspederm@gmail.com
Requires-Python: >=3.8,<4.0
Classifier: Programming Language :: Python :: 3
Classifier: Programming Language :: Python :: 3.8
Classifier: Programming Language :: Python :: 3.9
Classifier: Programming Language :: Python :: 3.10
Classifier: Programming Language :: Python :: 3.11
Requires-Dist: pydantic (>=1.10.5,<2.0.0)
Requires-Dist: pymsteams (>=0.2.2,<0.3.0)
Requires-Dist: python-dotenv (>=0.21.1,<0.22.0)
Requires-Dist: pyyaml (>=6.0,<7.0)
Requires-Dist: requests (>=2.28.2,<3.0.0)
Project-URL: Repository, https://github.com/JenspederM/ConnectMon
